LICENSE
MANIFEST.in
README.md
setup.py
hackerXconsole.egg-info/PKG-INFO
hackerXconsole.egg-info/SOURCES.txt
hackerXconsole.egg-info/dependency_links.txt
hackerXconsole.egg-info/requires.txt
hackerXconsole.egg-info/top_level.txt
web_console/__init__.py
web_console/admin.py
web_console/apps.py
web_console/models.py
web_console/tests.py
web_console/urls.py
web_console/views.py
web_console/static/console/css/console.css
web_console/static/console/css/miniAdmin.css
web_console/static/console/img/logo.png
web_console/static/console/js/console.js
web_console/static/console/js/miniAdmin.js
web_console/static/console/layui/layui.js
web_console/static/console/layui/css/layui.css
web_console/static/console/layui/font/iconfont.eot
web_console/static/console/layui/font/iconfont.svg
web_console/static/console/layui/font/iconfont.ttf
web_console/static/console/layui/font/iconfont.woff
web_console/static/console/layui/font/iconfont.woff2
web_console/templates/console/frame_base.html
web_console/templates/console/home.html
web_console/templates/console/layout.html
web_console/templates/console/login.html